{
  "active_markets": 1,
  "average_contracts_per_trade": 15.6,
  "average_entry_price": 0.215957,
  "configuration": {
    "base_share_increment": 1.0,
    "enable_dynamic_scaling": true,
    "fee_reserve": 0.05,
    "format_version": 17,
    "initial_position_size": 3.0,
    "live_absolute_stop_price": 0.05,
    "live_consecutive_loss_limit": 2,
    "live_execution_strategy": "settlement_contrarian_settlement_v2",
    "live_markets_to_skip_after_loss_limit": 2,
    "live_quote_max_age_seconds": 3.0,
    "market_refresh_seconds": 15.0,
    "max_active_markets": 1,
    "max_contracts_per_market": 30.0,
    "max_contracts_per_market_auto": true,
    "max_total_capital": 6.0,
    "max_total_capital_auto": true,
    "order_reconcile_seconds": 5.0,
    "poll_seconds": 2.0,
    "scaling_profit_multiplier": 16.5,
    "settlement_contrarian_entry_grace_seconds": 120.0,
    "status_log_seconds": 60.0,
    "watch_start_grace_seconds": 45.0
  },
  "current_streak": 1,
  "current_streak_kind": "loss",
  "dynamic_base_share_scaling": {
    "base_share_increment": 1.0,
    "current_base_share_count": 3.0,
    "current_ladder_rungs": {
      "0.1000": 12.0,
      "0.2000": 9.0,
      "0.3000": 6.0,
      "0.4000": 3.0
    },
    "enabled": true,
    "last_scale": null,
    "max_contracts_per_market_auto": true,
    "max_total_capital_auto": true,
    "profit_remaining_to_increase": 51.72,
    "profit_since_last_increase": -2.22,
    "required_profit": 49.5,
    "scale_count": 0,
    "scaling_profit_multiplier": 16.5,
    "starting_base_share_count": 3.0
  },
  "entry_loss_skip": {
    "consecutive_completed_losses": 1,
    "last_completed_trade": {
      "completed_at": "2026-07-24T19:42:42.535832+00:00",
      "net_profit_loss": -5.22,
      "ticker": "KXBTC15M-26JUL241545-45"
    },
    "last_reset_at": "2026-07-24T19:15:20.646925+00:00",
    "last_reset_reason": "completed_winning_trade",
    "loss_limit": 2,
    "markets_remaining_to_skip": 0,
    "markets_to_skip_after_limit": 2,
    "skip_armed_at": null,
    "triggering_ticker": null
  },
  "exit_policy": "hold every filled contract to settlement; only fresh full-depth selected-side bid <= $0.05 triggers a reduce-only close",
  "five_cent_stop_exits": 69,
  "generated_at": "2026-07-24T20:11:35.296316+00:00",
  "last_closed_trade": {
    "closed_at": "2026-07-24T19:42:42.535832+00:00",
    "contracts": 30.0,
    "exit_method": "live_reduce_only_absolute_5c_stop",
    "fees": 0.0,
    "gross_payout": 0.78,
    "net_profit_loss": -5.22,
    "return_percentage": -87.0,
    "selected_side": "no",
    "settlement_outcome": null,
    "ticker": "KXBTC15M-26JUL241545-45",
    "total_cost": 6.0
  },
  "longest_losing_streak": 8,
  "longest_winning_streak": 6,
  "losing_trades": 73,
  "markets_skipped_due_to_loss_circuit_breaker": 16,
  "markets_started": 177,
  "maximum_drawdown": 46.0166,
  "net_profit": 98.236319,
  "return_on_capital": 0.224304,
  "rung_order_activity": {
    "0.10": {
      "canceled_unfilled_orders": 76,
      "filled_contracts": 684.0,
      "filled_order_submissions": 81,
      "resting_orders": 3,
      "rung_price": 0.1,
      "submitted_contracts": 1352.0,
      "submitted_orders": 160
    },
    "0.20": {
      "canceled_unfilled_orders": 64,
      "filled_contracts": 612.0,
      "filled_order_submissions": 94,
      "resting_orders": 2,
      "rung_price": 0.2,
      "submitted_contracts": 1014.0,
      "submitted_orders": 160
    },
    "0.30": {
      "canceled_unfilled_orders": 45,
      "filled_contracts": 478.0,
      "filled_order_submissions": 111,
      "resting_orders": 2,
      "rung_price": 0.3,
      "submitted_contracts": 672.0,
      "submitted_orders": 158
    },
    "0.40": {
      "canceled_unfilled_orders": 29,
      "filled_contracts": 272.0,
      "filled_order_submissions": 128,
      "resting_orders": 0,
      "rung_price": 0.4,
      "submitted_contracts": 333.0,
      "submitted_orders": 157
    }
  },
  "rung_performance": {
    "0.10": {
      "breakeven_orders": 0,
      "filled_contracts": 684.0,
      "filled_orders": 81,
      "losing_contracts": 628.0,
      "losing_orders": 75,
      "net_profit": -12.4,
      "rung_price": 0.1,
      "win_rate": 0.074074,
      "winning_contracts": 56.0,
      "winning_orders": 6
    },
    "0.20": {
      "breakeven_orders": 0,
      "filled_contracts": 603.0,
      "filled_orders": 93,
      "losing_contracts": 474.0,
      "losing_orders": 76,
      "net_profit": 8.4,
      "rung_price": 0.2,
      "win_rate": 0.182796,
      "winning_contracts": 129.0,
      "winning_orders": 17
    },
    "0.30": {
      "breakeven_orders": 0,
      "filled_contracts": 472.0,
      "filled_orders": 110,
      "losing_contracts": 316.0,
      "losing_orders": 76,
      "net_profit": 14.2902,
      "rung_price": 0.3,
      "win_rate": 0.309091,
      "winning_contracts": 156.0,
      "winning_orders": 34
    },
    "0.40": {
      "breakeven_orders": 0,
      "filled_contracts": 269.0,
      "filled_orders": 127,
      "losing_contracts": 158.0,
      "losing_orders": 76,
      "net_profit": 2.7152,
      "rung_price": 0.4,
      "win_rate": 0.401575,
      "winning_contracts": 111.0,
      "winning_orders": 51
    }
  },
  "settled_trades": 130,
  "settlement_exits": 61,
  "strategy": "settlement_contrarian_settlement_v2",
  "total_contracts": 2028.0,
  "total_cost": 437.96,
  "unfilled_markets": 29,
  "win_rate": 0.438462,
  "winning_trades": 57
}
